datamaker_backup/__init__.py
datamaker_backup/connector.py
datamaker_backup/storage.py
datamaker_backup/utils.py
datamaker_backup-0.2.0.dist-info/LICENSE
datamaker_backup-0.2.0.dist-info/METADATA
datamaker_backup-0.2.0.dist-info/WHEEL
datamaker_backup-0.2.0.dist-info/top_level.txt
datamaker_backup-0.2.0.dist-info/RECORD
