Metadata-Version: 2.1
Name: datamaker-backup
Version: 0.2.0
Summary: datamaker backup
Home-page: https://www.datamaker.io
Author: datamaker
Author-email: developer@datamaker.io
License: MIT
Classifier: Programming Language :: Python :: 3
Classifier: License :: OSI Approved :: MIT License
Classifier: Operating System :: OS Independent
Classifier: Programming Language :: Python
Classifier: Programming Language :: Python :: 3.9
Classifier: Programming Language :: Python :: Implementation :: CPython
Classifier: Programming Language :: Python :: Implementation :: PyPy
Classifier: Topic :: Software Development :: Libraries :: Python Modules
Requires-Python: >=3.9
License-File: LICENSE
Requires-Dist: django >=4.2
Requires-Dist: django-dbbackup >=4.0.2
Requires-Dist: requests >=2.26.0
